pysesameos2/__init__.py
pysesameos2/ble.py
pysesameos2/chsesame2.py
pysesameos2/chsesamebot.py
pysesameos2/const.py
pysesameos2/crypto.py
pysesameos2/device.py
pysesameos2/helper.py
pysesameos2-0.0.6.dist-info/LICENSE
pysesameos2-0.0.6.dist-info/WHEEL
pysesameos2-0.0.6.dist-info/METADATA
pysesameos2-0.0.6.dist-info/RECORD
