Metadata-Version: 2.1
Name: pysesameos2
Version: 0.0.6
Summary: Unofficial library to control smart devices running Sesame OS2.
Home-page: https://github.com/mochipon/pysesameos2
License: MIT
Author: Masaki Tagawa
Author-email: masaki@tagawa.email
Requires-Python: >=3.7,<4.0
Classifier: Development Status :: 2 - Pre-Alpha
Classifier: Intended Audience :: Developers
Classifier: License :: OSI Approved :: MIT License
Classifier: Natural Language :: English
Classifier: Programming Language :: Python :: 3
Classifier: Programming Language :: Python :: 3.10
Classifier: Programming Language :: Python :: 3.7
Classifier: Programming Language :: Python :: 3.8
Classifier: Programming Language :: Python :: 3.9
Provides-Extra: doc
Requires-Dist: aenum (>=3.1.11,<4.0.0)
Requires-Dist: bleak (>=0.14.3,<0.15.0)
Requires-Dist: cryptography (>=37.0.2,<38.0.0)
Requires-Dist: importlib-metadata (>=4.11.4,<5.0.0); python_version < "3.8"
Requires-Dist: livereload (>=2.6.3,<3.0.0); extra == "doc"
Requires-Dist: mkdocs (>=1.3.0,<2.0.0); extra == "doc"
Requires-Dist: mkdocs-autorefs (>=0.4.1,<0.5.0); extra == "doc"
Requires-Dist: mkdocs-include-markdown-plugin (>=3.5.1,<4.0.0); extra == "doc"
Requires-Dist: mkdocs-material (>=8.2.15,<9.0.0); extra == "doc"
Requires-Dist: mkdocstrings (>=0.19.0,<0.20.0); extra == "doc"
Requires-Dist: mkdocstrings-python (>=0.7.0,<0.8.0); extra == "doc"
Requires-Dist: typing-extensions (>=4.2.0,<5.0.0); python_version < "3.8"
